sitebay_mcp/__init__.py
sitebay_mcp/auth.py
sitebay_mcp/client.py
sitebay_mcp/exceptions.py
sitebay_mcp/resources.py
sitebay_mcp/server.py
sitebay_mcp/tools/__init__.py
sitebay_mcp/tools/operations.py
sitebay_mcp/tools/sites.py
sitebay_mcp-0.1.1758486955.dist-info/METADATA
sitebay_mcp-0.1.1758486955.dist-info/WHEEL
sitebay_mcp-0.1.1758486955.dist-info/entry_points.txt
sitebay_mcp-0.1.1758486955.dist-info/licenses/LICENSE
sitebay_mcp-0.1.1758486955.dist-info/RECORD
