Metadata-Version: 2.4
Name: sitebay-mcp
Version: 0.1.1758486955
Summary: SiteBay MCP Server - WordPress hosting management through Claude Code
Author-email: SiteBay <support@sitebay.org>
License-File: LICENSE
Requires-Python: >=3.11
Requires-Dist: fastmcp>=2.9.2
Requires-Dist: httpx>=0.27.0
Requires-Dist: pydantic>=2.0.0
Requires-Dist: python-dotenv>=1.0.0
Requires-Dist: sse-starlette>=2.2.1
Requires-Dist: starlette>=0.45.0
Requires-Dist: typing-extensions>=4.0.0
Requires-Dist: uvicorn>=0.34.0
Provides-Extra: dev
Requires-Dist: black>=23.0.0; extra == 'dev'
Requires-Dist: pytest-asyncio>=0.21.0; extra == 'dev'
Requires-Dist: pytest>=7.0.0; extra == 'dev'
Requires-Dist: ruff>=0.1.0; extra == 'dev'
